cruxpy/__init__.py
cruxpy/portspage.py
cruxpy/repo.py
cruxpy/examples/cli.py
cruxpy/examples/make_ports_page.py
cruxpy/files/header.html
cruxpy-0.1.4.dist-info/licenses/LICENSE
cruxpy-0.1.4.dist-info/METADATA
cruxpy-0.1.4.dist-info/WHEEL
cruxpy-0.1.4.dist-info/top_level.txt
cruxpy-0.1.4.dist-info/RECORD
