Metadata-Version: 2.4
Name: cruxpy
Version: 0.1.4
Summary: Help building a webpage for Crux ports repository
Author-email: Wawrzyniec Niewodniczański <main@wawrzek.name>
License-Expression: GPL-3.0-only
Project-URL: repository, https://github.com/wawrzek/cruxpy
Classifier: Development Status :: 4 - Beta
Classifier: Intended Audience :: Developers
Classifier: Operating System :: POSIX :: Linux
Classifier: Programming Language :: Python :: 3
Classifier: Programming Language :: Python :: 3.12
Classifier: Topic :: System :: Installation/Setup
Classifier: Topic :: System :: Software Distribution
Classifier: Topic :: System :: Systems Administration
Classifier: Topic :: Utilities
Requires-Python: >=3.12
License-File: LICENSE
Requires-Dist: GitPython
Dynamic: license-file
